pycord/ipc/__init__.py
pycord/ipc/client.py
pycord/ipc/errors.py
pycord/ipc/py.typed
pycord/ipc/server.py
pycord_inter_process-0.1.5.dist-info/licenses/LICENSE
pycord_inter_process-0.1.5.dist-info/METADATA
pycord_inter_process-0.1.5.dist-info/WHEEL
pycord_inter_process-0.1.5.dist-info/top_level.txt
pycord_inter_process-0.1.5.dist-info/RECORD
